spec2nii/__init__.py
spec2nii/_version.py
spec2nii/anonymise.py
spec2nii/bruker.py
spec2nii/bruker_fid_override.json
spec2nii/bruker_properties.json
spec2nii/due.py
spec2nii/fileiobase.py
spec2nii/jmrui.py
spec2nii/nifti_orientation.py
spec2nii/other.py
spec2nii/other_formats.py
spec2nii/spec2nii.py
spec2nii/uih.py
spec2nii/varian.py
spec2nii/varian_importer.py
spec2nii/GE/VESPA_LICENSE
spec2nii/GE/__init__.py
spec2nii/GE/ge_hdr_fields.py
spec2nii/GE/ge_pfile.py
spec2nii/GE/ge_read_pfile.py
spec2nii/GSL/__init__.py
spec2nii/GSL/gslfunctions.py
spec2nii/Philips/__init__.py
spec2nii/Philips/philips.py
spec2nii/Philips/philips_data_list.py
spec2nii/Philips/philips_dcm.py
spec2nii/Siemens/__init__.py
spec2nii/Siemens/dicomfunctions.py
spec2nii/Siemens/rda.py
spec2nii/Siemens/twix_special_case.py
spec2nii/Siemens/twixfunctions.py
spec2nii/dcm2niiOrientation/__init__.py
spec2nii/dcm2niiOrientation/orientationFuncs.py
spec2nii-0.8.7.dist-info/licenses/LICENSE
spec2nii-0.8.7.dist-info/METADATA
spec2nii-0.8.7.dist-info/WHEEL
spec2nii-0.8.7.dist-info/entry_points.txt
spec2nii-0.8.7.dist-info/top_level.txt
spec2nii-0.8.7.dist-info/RECORD
