Metadata-Version: 2.4
Name: spec2nii
Version: 0.8.7
Summary: Multi-format in vivo MR spectroscopy conversion to NIFTI
Home-page: https://github.com/wtclarke/spec2nii
Author: Will Clarke
Author-email: william.clarke@ndcn.ox.ac.uk
Classifier: Programming Language :: Python :: 3
Classifier: Programming Language :: Python :: 3.9
Classifier: Programming Language :: Python :: 3.10
Classifier: Programming Language :: Python :: 3.11
Classifier: Programming Language :: Python :: 3.12
Classifier: Programming Language :: Python :: 3.13
Classifier: License :: OSI Approved :: BSD License
Classifier: Operating System :: OS Independent
Requires-Python: >=3.9
License-File: LICENSE
Requires-Dist: numpy>=1.26
Requires-Dist: nibabel
Requires-Dist: pydicom==3.*; python_version >= "3.10"
Requires-Dist: pydicom==2.4.*; python_version < "3.10"
Requires-Dist: pyMapVBVD>=0.6.0
Requires-Dist: scipy>=1.13
Requires-Dist: brukerapi>=0.1.8
Requires-Dist: pandas
Requires-Dist: nifti-mrs>=1.3.2
Dynamic: author
Dynamic: author-email
Dynamic: classifier
Dynamic: description
Dynamic: description-content-type
Dynamic: home-page
Dynamic: license-file
Dynamic: requires-dist
Dynamic: requires-python
Dynamic: summary
